blib/__init__.py
blib/application.py
blib/cache.py
blib/date.py
blib/enums.py
blib/errors.py
blib/jsonipc.py
blib/misc.py
blib/objects.py
blib/path.py
blib/py.typed
blib/termutils.py
blib/transport.py
blib/url.py
blib/http/__init__.py
blib/http/async_client.py
blib/http/message.py
blib/http/misc.py
barkshark_lib-0.2.5.post1.dist-info/LICENSE
barkshark_lib-0.2.5.post1.dist-info/METADATA
barkshark_lib-0.2.5.post1.dist-info/WHEEL
barkshark_lib-0.2.5.post1.dist-info/top_level.txt
barkshark_lib-0.2.5.post1.dist-info/RECORD
